kitano/__init__.py
kitano/logs/__init__.py
kitano/logs/logging.py
tests/__init__.py
tests/test.py
tests/test_termux.py
tests/test_browser/__init__.py
tests/test_browser/test_google.py
tests/test_browser/test_proxy.py
kitano-0.0.8.5.dist-info/LICENSE
kitano-0.0.8.5.dist-info/METADATA
kitano-0.0.8.5.dist-info/WHEEL
kitano-0.0.8.5.dist-info/top_level.txt
kitano-0.0.8.5.dist-info/RECORD
