Metadata-Version: 2.1
Name: kitano
Version: 0.0.8.5
Summary: Library for development and works in python3.9+
Home-page: https://github.com/reinanbr/kitano
Author: Reinan Br
Author-email: slimchatuba@gmail.com
License: MIT License
Keywords: kit tools dev works
License-File: LICENSE
Requires-Dist: colorama
